PyATEMMax/ATEMBuffer.py
PyATEMMax/ATEMCommandHandlers.py
PyATEMMax/ATEMConnectionManager.py
PyATEMMax/ATEMConstant.py
PyATEMMax/ATEMException.py
PyATEMMax/ATEMMax.py
PyATEMMax/ATEMProtocol.py
PyATEMMax/ATEMProtocolEnums.py
PyATEMMax/ATEMSetterMethods.py
PyATEMMax/ATEMSocket.py
PyATEMMax/ATEMSwitcherState.py
PyATEMMax/ATEMUtils.py
PyATEMMax/ATEMValueDict.py
PyATEMMax/__init__.py
PyATEMMax/StateData/AudioMixer.py
PyATEMMax/StateData/AuxSource.py
PyATEMMax/StateData/CameraControl.py
PyATEMMax/StateData/ClipPlayer.py
PyATEMMax/StateData/ColorGenerator.py
PyATEMMax/StateData/DownConverter.py
PyATEMMax/StateData/DownStreamKeyer.py
PyATEMMax/StateData/FadeToBlack.py
PyATEMMax/StateData/InputProperties.py
PyATEMMax/StateData/Key.py
PyATEMMax/StateData/Keyer.py
PyATEMMax/StateData/LastStateChange.py
PyATEMMax/StateData/Macro.py
PyATEMMax/StateData/MediaPlayer.py
PyATEMMax/StateData/MediaPoolStorage.py
PyATEMMax/StateData/MixEffect.py
PyATEMMax/StateData/MultiViewer.py
PyATEMMax/StateData/Power.py
PyATEMMax/StateData/PreviewInput.py
PyATEMMax/StateData/ProgramInput.py
PyATEMMax/StateData/ProtocolVersion.py
PyATEMMax/StateData/SuperSource.py
PyATEMMax/StateData/Tally.py
PyATEMMax/StateData/Topology.py
PyATEMMax/StateData/Transition.py
PyATEMMax/StateData/VideoMixer.py
PyATEMMax/StateData/VideoMode.py
PyATEMMax/StateData/__init__.py
PyATEMMax-1.0b2.dist-info/LICENSE.md
PyATEMMax-1.0b2.dist-info/METADATA
PyATEMMax-1.0b2.dist-info/WHEEL
PyATEMMax-1.0b2.dist-info/top_level.txt
PyATEMMax-1.0b2.dist-info/zip-safe
PyATEMMax-1.0b2.dist-info/RECORD
