Metadata-Version: 2.1
Name: PyATEMMax
Version: 1.0b2
Summary: A Python library to monitor and control Blackmagic Design ATEM video switchers.
Home-page: https://github.com/clvLabs/PyATEMMax
Author: Tony Aguilar
Author-email: onixag@gmail.com
License: GPL
Platform: any
Classifier: Programming Language :: Python :: 3
Classifier: License :: OSI Approved :: GNU General Public License (GPL)
Classifier: Operating System :: OS Independent
Classifier: Development Status :: 3 - Alpha
